{
  "$schema": "./node_modules/@biomejs/biome/configuration_schema.json",
  "organizeImports": {
    "enabled": false
  },
  "linter": {
    "enabled": true,
    "rules": {
      "recommended": false,
      "suspicious": {
        "noControlCharactersInRegex": "error",
        "useGetterReturn": "error",
        "noDuplicateObjectKeys": "error",
        "noImportAssign": "error",
        "noDebugger": "error",
        "noShadowRestrictedNames": "error",
        "noSelfCompare": "error",
        "noClassAssign": "error",
        "useDefaultSwitchClauseLast": "error",
        "noCatchAssign": "error",
        "noFallthroughSwitchClause": "error",
        "noPrototypeBuiltins": "error",
        "noExtraNonNullAssertion": "error",
        "noRedeclare": "error",
        "noUnsafeDeclarationMerging": "error",
        "useNamespaceKeyword": "error",
        "useValidTypeof": "error",
        "noGlobalAssign": "error",
        "noMisleadingCharacterClass": "error"
      },
      "complexity": {
        "noMultipleSpacesInRegularExpressionLiterals": "error",
        "useArrowFunction": "error",
        "useRegexLiterals": "error",
        "noUselessCatch": "error",
        "noVoid": "error",
        "noStaticOnlyClass": "error",
        "noUselessThisAlias": "error",
        "noUselessTypeConstraint": "error",
        "noUselessConstructor": "error",
        "noUselessEmptyExport": "error",
        "useOptionalChain": "error",
        "noUselessLoneBlockStatements": "error"
      },
      "correctness": {
        "noUnreachable": "error",
        "noInvalidConstructorSuper": "error",
        "noUnsafeOptionalChaining": "error",
        "noUnreachableSuper": "error",
        "noUnsafeFinally": "error",
        "noConstantCondition": "error",
        "noGlobalObjectCalls": "error",
        "noSetterReturn": "error",
        "noSelfAssign": "error",
        "noConstAssign": "error",
        "useYield": "error",
        "noUnusedLabels": "error",
        "useValidForDirection": "error",
        "noEmptyCharacterClassInRegex": "error",
        "useIsNan": "error"
      },
      "style": {
        "useSingleVarDeclarator": "error",
        "useBlockStatements": "error",
        "useConst": "error",
        "noRestrictedGlobals": "error",
        "useExponentiationOperator": "error",
        "useNumericLiterals": "error",
        "noCommaOperator": "error",
        "useCollapsedElseIf": "error",
        "noInferrableTypes": "error",
        "noNamespace": "error",
        "useAsConstAssertion": "error",
        "useLiteralEnumMembers": "error"
      },
      "security": {
        "noGlobalEval": "error"
      },
      "nursery": {
        "noUselessTernary": "error"
      }
    }
  },
  "formatter": {
    "enabled": true,
    "formatWithErrors": true,
    "indentStyle": "space",
    "indentWidth": 2,
    "lineEnding": "lf"
  },
  "json": {
    "formatter": {
      "enabled": true,
      "lineWidth": 100
    }
  },
  "javascript": {
    "formatter": {
      "enabled": true,
      "lineWidth": 100,
      "quoteStyle": "single",
      "jsxQuoteStyle": "double",
      "quoteProperties": "asNeeded",
      "trailingComma": "all",
      "semicolons": "always",
      "arrowParentheses": "asNeeded",
      "bracketSpacing": true,
      "bracketSameLine": false
    }
  }
}
